<?xml version="1.0" encoding="UTF-8"?>
<BaliMessageLog>
    <Task name="Map">
        <Message>
            <ID>51001030</ID>
            <Severity>Warning</Severity>
            <Dynamic>i_sys_rst</Dynamic>
        </Message>
        <Message>
            <ID>51001051</ID>
            <Severity>Warning</Severity>
            <Dynamic>top_reveal_coretop_instance/top_la0_inst_0/trig_u/te_0/pmi_ram_dpXO3Lbinarynonespeedasyncdisablereg112112/pmi_ram_dpXbnonesadr11211211528818_0_0_0</Dynamic>
        </Message>
    </Task>
    <Task name="Lattice_Synthesis">
        <Message>
            <ID>2120344</ID>
            <Severity>Info</Severity>
            <Dynamic>2</Dynamic>
        </Message>
        <Message>
            <ID>2120346</ID>
            <Severity>Info</Severity>
            <Dynamic>0</Dynamic>
        </Message>
        <Message>
            <ID>35901018</ID>
            <Severity>Info</Severity>
            <Dynamic>C:/Users/SEC29/Desktop/i2s_iot/rvl_test/top_i2stest.v(1): </Dynamic>
            <Dynamic>top</Dynamic>
            <Navigation>C:/Users/SEC29/Desktop/i2s_iot/rvl_test/top_i2stest.v</Navigation>
            <Navigation>1</Navigation>
        </Message>
        <Message>
            <ID>35909000</ID>
            <Severity>Info</Severity>
            <Dynamic>C:/Users/SEC29/Desktop/i2s_iot/rvl_test/top_i2stest.v(89): </Dynamic>
            <Dynamic>top</Dynamic>
            <Navigation>C:/Users/SEC29/Desktop/i2s_iot/rvl_test/top_i2stest.v</Navigation>
            <Navigation>89</Navigation>
        </Message>
        <Message>
            <ID>35909000</ID>
            <Severity>Info</Severity>
            <Dynamic>C:/Users/SEC29/Desktop/i2s_iot/rvl_test/i2s_cont.v(82): </Dynamic>
            <Dynamic>I2S_Controller_uniq_1</Dynamic>
            <Navigation>C:/Users/SEC29/Desktop/i2s_iot/rvl_test/i2s_cont.v</Navigation>
            <Navigation>82</Navigation>
        </Message>
        <Message>
            <ID>35909000</ID>
            <Severity>Info</Severity>
            <Dynamic>C:/Users/SEC29/Desktop/i2s_iot/rvl_test/i2s_cont.v(82): </Dynamic>
            <Dynamic>I2S_Controller_uniq_2</Dynamic>
            <Navigation>C:/Users/SEC29/Desktop/i2s_iot/rvl_test/i2s_cont.v</Navigation>
            <Navigation>82</Navigation>
        </Message>
        <Message>
            <ID>35909000</ID>
            <Severity>Info</Severity>
            <Dynamic>C:/Users/SEC29/Desktop/i2s_iot/rvl_test/pll1.v(104): </Dynamic>
            <Dynamic>pll1_uniq_1</Dynamic>
            <Navigation>C:/Users/SEC29/Desktop/i2s_iot/rvl_test/pll1.v</Navigation>
            <Navigation>104</Navigation>
        </Message>
        <Message>
            <ID>35909000</ID>
            <Severity>Info</Severity>
            <Dynamic>C:/Users/SEC29/Desktop/i2s_iot/rvl_test/clk_div.v(37): </Dynamic>
            <Dynamic>clk_div_uniq_1</Dynamic>
            <Navigation>C:/Users/SEC29/Desktop/i2s_iot/rvl_test/clk_div.v</Navigation>
            <Navigation>37</Navigation>
        </Message>
        <Message>
            <ID>35909000</ID>
            <Severity>Info</Severity>
            <Dynamic>C:/Users/SEC29/Desktop/i2s_iot/rvl_test/i2s_rx.v(180): </Dynamic>
            <Dynamic>i2s_rx_uniq_1</Dynamic>
            <Navigation>C:/Users/SEC29/Desktop/i2s_iot/rvl_test/i2s_rx.v</Navigation>
            <Navigation>180</Navigation>
        </Message>
        <Message>
            <ID>35909000</ID>
            <Severity>Info</Severity>
            <Dynamic>C:/Users/SEC29/Desktop/i2s_iot/rvl_test/i2s_rx.v(180): </Dynamic>
            <Dynamic>i2s_rx_uniq_2</Dynamic>
            <Navigation>C:/Users/SEC29/Desktop/i2s_iot/rvl_test/i2s_rx.v</Navigation>
            <Navigation>180</Navigation>
        </Message>
        <Message>
            <ID>35002000</ID>
            <Severity>Info</Severity>
        </Message>
        <Message>
            <ID>35001781</ID>
            <Severity>Info</Severity>
        </Message>
        <Message>
            <ID>35935034</ID>
            <Severity>Warning</Severity>
            <Dynamic>c:/users/sec29/desktop/i2s_iot/rvl_test/impl1/reveal_workspace/tmpreveal/top_rvl.v(77): </Dynamic>
            <Dynamic>port2</Dynamic>
            <Navigation>c:/users/sec29/desktop/i2s_iot/rvl_test/impl1/reveal_workspace/tmpreveal/top_rvl.v</Navigation>
            <Navigation>77</Navigation>
        </Message>
        <Message>
            <ID>35001611</ID>
            <Severity>Warning</Severity>
        </Message>
        <Message>
            <ID>1166052</ID>
            <Severity>Warning</Severity>
            <Dynamic>logical</Dynamic>
            <Dynamic>top_reveal_coretop_instance/jupdate[0]</Dynamic>
            <Navigation>top_reveal_coretop_instance/jupdate[0]</Navigation>
        </Message>
        <Message>
            <ID>1166052</ID>
            <Severity>Warning</Severity>
            <Dynamic>logical</Dynamic>
            <Dynamic>xo2chub/tdoa</Dynamic>
            <Navigation>xo2chub/tdoa</Navigation>
        </Message>
        <Message>
            <ID>1166052</ID>
            <Severity>Warning</Severity>
            <Dynamic>logical</Dynamic>
            <Dynamic>xo2chub/cdn</Dynamic>
            <Navigation>xo2chub/cdn</Navigation>
        </Message>
        <Message>
            <ID>1166052</ID>
            <Severity>Warning</Severity>
            <Dynamic>logical</Dynamic>
            <Dynamic>xo2chub/ip_enable[15]</Dynamic>
            <Navigation>xo2chub/ip_enable[15]</Navigation>
        </Message>
        <Message>
            <ID>1166052</ID>
            <Severity>Warning</Severity>
            <Dynamic>logical</Dynamic>
            <Dynamic>xo2chub/genblk7.un1_jtagf_u</Dynamic>
            <Navigation>xo2chub/genblk7.un1_jtagf_u</Navigation>
        </Message>
        <Message>
            <ID>1166052</ID>
            <Severity>Warning</Severity>
            <Dynamic>logical</Dynamic>
            <Dynamic>xo2chub/genblk7.un1_jtagf_u_1</Dynamic>
            <Navigation>xo2chub/genblk7.un1_jtagf_u_1</Navigation>
        </Message>
        <Message>
            <ID>1166052</ID>
            <Severity>Warning</Severity>
            <Dynamic>logical</Dynamic>
            <Dynamic>xo2chub/bit_count_cry_0_S0[0]</Dynamic>
            <Navigation>xo2chub/bit_count_cry_0_S0[0]</Navigation>
        </Message>
        <Message>
            <ID>1166052</ID>
            <Severity>Warning</Severity>
            <Dynamic>logical</Dynamic>
            <Dynamic>xo2chub/bit_count_cry_0_COUT[3]</Dynamic>
            <Navigation>xo2chub/bit_count_cry_0_COUT[3]</Navigation>
        </Message>
        <Message>
            <ID>1166052</ID>
            <Severity>Warning</Severity>
            <Dynamic>logical</Dynamic>
            <Dynamic>xo2chub/rom_rd_addr_cry_0_S0[0]</Dynamic>
            <Navigation>xo2chub/rom_rd_addr_cry_0_S0[0]</Navigation>
        </Message>
        <Message>
            <ID>1166052</ID>
            <Severity>Warning</Severity>
            <Dynamic>logical</Dynamic>
            <Dynamic>xo2chub/rom_rd_addr_s_0_S1[7]</Dynamic>
            <Navigation>xo2chub/rom_rd_addr_s_0_S1[7]</Navigation>
        </Message>
        <Message>
            <ID>1166052</ID>
            <Severity>Warning</Severity>
            <Dynamic>logical</Dynamic>
            <Dynamic>xo2chub/rom_rd_addr_s_0_COUT[7]</Dynamic>
            <Navigation>xo2chub/rom_rd_addr_s_0_COUT[7]</Navigation>
        </Message>
        <Message>
            <ID>1166052</ID>
            <Severity>Warning</Severity>
            <Dynamic>logical</Dynamic>
            <Dynamic>xo2chub/jtdo2_int_prm_16_0_0_S0</Dynamic>
            <Navigation>xo2chub/jtdo2_int_prm_16_0_0_S0</Navigation>
        </Message>
        <Message>
            <ID>1166052</ID>
            <Severity>Warning</Severity>
            <Dynamic>logical</Dynamic>
            <Dynamic>xo2chub/jtdo2_int_prm_16_0_0_S1</Dynamic>
            <Navigation>xo2chub/jtdo2_int_prm_16_0_0_S1</Navigation>
        </Message>
        <Message>
            <ID>1166052</ID>
            <Severity>Warning</Severity>
            <Dynamic>logical</Dynamic>
            <Dynamic>xo2chub/jtdo2_int_prm_15_0_0_S0</Dynamic>
            <Navigation>xo2chub/jtdo2_int_prm_15_0_0_S0</Navigation>
        </Message>
        <Message>
            <ID>1166052</ID>
            <Severity>Warning</Severity>
            <Dynamic>logical</Dynamic>
            <Dynamic>xo2chub/jtdo2_int_prm_15_0_0_S1</Dynamic>
            <Navigation>xo2chub/jtdo2_int_prm_15_0_0_S1</Navigation>
        </Message>
        <Message>
            <ID>1166052</ID>
            <Severity>Warning</Severity>
            <Dynamic>logical</Dynamic>
            <Dynamic>xo2chub/jtdo2_int_prm_13_0_0_S0</Dynamic>
            <Navigation>xo2chub/jtdo2_int_prm_13_0_0_S0</Navigation>
        </Message>
        <Message>
            <ID>1166052</ID>
            <Severity>Warning</Severity>
            <Dynamic>logical</Dynamic>
            <Dynamic>xo2chub/jtdo2_int_prm_13_0_0_S1</Dynamic>
            <Navigation>xo2chub/jtdo2_int_prm_13_0_0_S1</Navigation>
        </Message>
        <Message>
            <ID>1166052</ID>
            <Severity>Warning</Severity>
            <Dynamic>logical</Dynamic>
            <Dynamic>xo2chub/jtdo2_int_prm_11_0_0_S0</Dynamic>
            <Navigation>xo2chub/jtdo2_int_prm_11_0_0_S0</Navigation>
        </Message>
        <Message>
            <ID>1166052</ID>
            <Severity>Warning</Severity>
            <Dynamic>logical</Dynamic>
            <Dynamic>xo2chub/jtdo2_int_prm_11_0_0_S1</Dynamic>
            <Navigation>xo2chub/jtdo2_int_prm_11_0_0_S1</Navigation>
        </Message>
        <Message>
            <ID>1166052</ID>
            <Severity>Warning</Severity>
            <Dynamic>logical</Dynamic>
            <Dynamic>xo2chub/jtdo2_int_prm_9_0_0_S0</Dynamic>
            <Navigation>xo2chub/jtdo2_int_prm_9_0_0_S0</Navigation>
        </Message>
        <Message>
            <ID>1166052</ID>
            <Severity>Warning</Severity>
            <Dynamic>logical</Dynamic>
            <Dynamic>xo2chub/jtdo2_int_prm_9_0_0_S1</Dynamic>
            <Navigation>xo2chub/jtdo2_int_prm_9_0_0_S1</Navigation>
        </Message>
        <Message>
            <ID>1166052</ID>
            <Severity>Warning</Severity>
            <Dynamic>logical</Dynamic>
            <Dynamic>xo2chub/jtdo2_int_prm_7_0_0_S0</Dynamic>
            <Navigation>xo2chub/jtdo2_int_prm_7_0_0_S0</Navigation>
        </Message>
        <Message>
            <ID>1166052</ID>
            <Severity>Warning</Severity>
            <Dynamic>logical</Dynamic>
            <Dynamic>xo2chub/jtdo2_int_prm_7_0_0_S1</Dynamic>
            <Navigation>xo2chub/jtdo2_int_prm_7_0_0_S1</Navigation>
        </Message>
        <Message>
            <ID>1166052</ID>
            <Severity>Warning</Severity>
            <Dynamic>logical</Dynamic>
            <Dynamic>xo2chub/jtdo2_int_prm_5_0_0_S0</Dynamic>
            <Navigation>xo2chub/jtdo2_int_prm_5_0_0_S0</Navigation>
        </Message>
        <Message>
            <ID>1166052</ID>
            <Severity>Warning</Severity>
            <Dynamic>logical</Dynamic>
            <Dynamic>xo2chub/jtdo2_int_prm_5_0_0_S1</Dynamic>
            <Navigation>xo2chub/jtdo2_int_prm_5_0_0_S1</Navigation>
        </Message>
        <Message>
            <ID>1166052</ID>
            <Severity>Warning</Severity>
            <Dynamic>logical</Dynamic>
            <Dynamic>xo2chub/jtdo2_int_prm_3_0_0_S0</Dynamic>
            <Navigation>xo2chub/jtdo2_int_prm_3_0_0_S0</Navigation>
        </Message>
        <Message>
            <ID>1166052</ID>
            <Severity>Warning</Severity>
            <Dynamic>logical</Dynamic>
            <Dynamic>xo2chub/jtdo2_int_prm_3_0_0_S1</Dynamic>
            <Navigation>xo2chub/jtdo2_int_prm_3_0_0_S1</Navigation>
        </Message>
        <Message>
            <ID>1166052</ID>
            <Severity>Warning</Severity>
            <Dynamic>logical</Dynamic>
            <Dynamic>xo2chub/jtdo2_int_prm_1_0_0_S0</Dynamic>
            <Navigation>xo2chub/jtdo2_int_prm_1_0_0_S0</Navigation>
        </Message>
        <Message>
            <ID>1166052</ID>
            <Severity>Warning</Severity>
            <Dynamic>logical</Dynamic>
            <Dynamic>xo2chub/jtdo2_int_prm_1_0_0_COUT</Dynamic>
            <Navigation>xo2chub/jtdo2_int_prm_1_0_0_COUT</Navigation>
        </Message>
        <Message>
            <ID>1163101</ID>
            <Severity>Warning</Severity>
            <Dynamic>29</Dynamic>
        </Message>
    </Task>
    <Task name="PAR">
        <Message>
            <ID>61001101</ID>
            <Severity>Warning</Severity>
        </Message>
        <Message>
            <ID>61061045</ID>
            <Severity>Warning</Severity>
        </Message>
        <Message>
            <ID>66011008</ID>
            <Severity>Warning</Severity>
            <Dynamic>
   Signal=osc_clk loads=1 clock_loads=1</Dynamic>
        </Message>
        <Message>
            <ID>66011008</ID>
            <Severity>Warning</Severity>
            <Dynamic>
   Signal=osc_clk loads=1 clock_loads=1</Dynamic>
        </Message>
    </Task>
    <Task name="Translate">
        <Message>
            <ID>1166052</ID>
            <Severity>Warning</Severity>
            <Dynamic>logical</Dynamic>
            <Dynamic>up_down_counter_reveal_coretop_instance/up_down_counter_la0_inst_0/trig_u/te_0/te_precnt_cry_0_S0[0]</Dynamic>
            <Navigation>up_down_counter_reveal_coretop_instance/up_down_counter_la0_inst_0/trig_u/te_0/te_precnt_cry_0_S0[0]</Navigation>
        </Message>
        <Message>
            <ID>1166052</ID>
            <Severity>Warning</Severity>
            <Dynamic>logical</Dynamic>
            <Dynamic>up_down_counter_reveal_coretop_instance/up_down_counter_la0_inst_0/trig_u/te_0/te_precnt_s_0_S1[15]</Dynamic>
            <Navigation>up_down_counter_reveal_coretop_instance/up_down_counter_la0_inst_0/trig_u/te_0/te_precnt_s_0_S1[15]</Navigation>
        </Message>
        <Message>
            <ID>1166052</ID>
            <Severity>Warning</Severity>
            <Dynamic>logical</Dynamic>
            <Dynamic>up_down_counter_reveal_coretop_instance/up_down_counter_la0_inst_0/trig_u/te_0/te_precnt_s_0_COUT[15]</Dynamic>
            <Navigation>up_down_counter_reveal_coretop_instance/up_down_counter_la0_inst_0/trig_u/te_0/te_precnt_s_0_COUT[15]</Navigation>
        </Message>
        <Message>
            <ID>1166052</ID>
            <Severity>Warning</Severity>
            <Dynamic>logical</Dynamic>
            <Dynamic>up_down_counter_reveal_coretop_instance/up_down_counter_la0_inst_0/trig_u/GND</Dynamic>
            <Navigation>up_down_counter_reveal_coretop_instance/up_down_counter_la0_inst_0/trig_u/GND</Navigation>
        </Message>
        <Message>
            <ID>1166052</ID>
            <Severity>Warning</Severity>
            <Dynamic>logical</Dynamic>
            <Dynamic>up_down_counter_reveal_coretop_instance/up_down_counter_la0_inst_0/trig_u/rd_dout_tcnt[4]</Dynamic>
            <Navigation>up_down_counter_reveal_coretop_instance/up_down_counter_la0_inst_0/trig_u/rd_dout_tcnt[4]</Navigation>
        </Message>
        <Message>
            <ID>1166052</ID>
            <Severity>Warning</Severity>
            <Dynamic>logical</Dynamic>
            <Dynamic>up_down_counter_reveal_coretop_instance/up_down_counter_la0_inst_0/trig_u/VCC</Dynamic>
            <Navigation>up_down_counter_reveal_coretop_instance/up_down_counter_la0_inst_0/trig_u/VCC</Navigation>
        </Message>
        <Message>
            <ID>1166052</ID>
            <Severity>Warning</Severity>
            <Dynamic>logical</Dynamic>
            <Dynamic>up_down_counter_reveal_coretop_instance/up_down_counter_la0_inst_0/trig_u/rd_dout_tu[3]</Dynamic>
            <Navigation>up_down_counter_reveal_coretop_instance/up_down_counter_la0_inst_0/trig_u/rd_dout_tu[3]</Navigation>
        </Message>
        <Message>
            <ID>1166052</ID>
            <Severity>Warning</Severity>
            <Dynamic>logical</Dynamic>
            <Dynamic>up_down_counter_reveal_coretop_instance/up_down_counter_la0_inst_0/jtag_int_u/bit_cnt_cry_0_S0[0]</Dynamic>
            <Navigation>up_down_counter_reveal_coretop_instance/up_down_counter_la0_inst_0/jtag_int_u/bit_cnt_cry_0_S0[0]</Navigation>
        </Message>
        <Message>
            <ID>1166052</ID>
            <Severity>Warning</Severity>
            <Dynamic>logical</Dynamic>
            <Dynamic>up_down_counter_reveal_coretop_instance/up_down_counter_la0_inst_0/jtag_int_u/bit_cnt_s_0_S1[5]</Dynamic>
            <Navigation>up_down_counter_reveal_coretop_instance/up_down_counter_la0_inst_0/jtag_int_u/bit_cnt_s_0_S1[5]</Navigation>
        </Message>
        <Message>
            <ID>1166052</ID>
            <Severity>Warning</Severity>
            <Dynamic>logical</Dynamic>
            <Dynamic>up_down_counter_reveal_coretop_instance/up_down_counter_la0_inst_0/jtag_int_u/bit_cnt_s_0_COUT[5]</Dynamic>
            <Navigation>up_down_counter_reveal_coretop_instance/up_down_counter_la0_inst_0/jtag_int_u/bit_cnt_s_0_COUT[5]</Navigation>
        </Message>
        <Message>
            <ID>1166052</ID>
            <Severity>Warning</Severity>
            <Dynamic>logical</Dynamic>
            <Dynamic>up_down_counter_reveal_coretop_instance/up_down_counter_la0_inst_0/tm_u/tm_wr_addr_cntr_cry_0_S0[0]</Dynamic>
            <Navigation>up_down_counter_reveal_coretop_instance/up_down_counter_la0_inst_0/tm_u/tm_wr_addr_cntr_cry_0_S0[0]</Navigation>
        </Message>
        <Message>
            <ID>1166052</ID>
            <Severity>Warning</Severity>
            <Dynamic>logical</Dynamic>
            <Dynamic>up_down_counter_reveal_coretop_instance/up_down_counter_la0_inst_0/tm_u/tm_wr_addr_cntr_s_0_S1[7]</Dynamic>
            <Navigation>up_down_counter_reveal_coretop_instance/up_down_counter_la0_inst_0/tm_u/tm_wr_addr_cntr_s_0_S1[7]</Navigation>
        </Message>
        <Message>
            <ID>1166052</ID>
            <Severity>Warning</Severity>
            <Dynamic>logical</Dynamic>
            <Dynamic>up_down_counter_reveal_coretop_instance/up_down_counter_la0_inst_0/tm_u/tm_wr_addr_cntr_s_0_COUT[7]</Dynamic>
            <Navigation>up_down_counter_reveal_coretop_instance/up_down_counter_la0_inst_0/tm_u/tm_wr_addr_cntr_s_0_COUT[7]</Navigation>
        </Message>
        <Message>
            <ID>1166052</ID>
            <Severity>Warning</Severity>
            <Dynamic>logical</Dynamic>
            <Dynamic>up_down_counter_reveal_coretop_instance/up_down_counter_la0_inst_0/tm_u/pre_trig_cntr_cry_0_S0[0]</Dynamic>
            <Navigation>up_down_counter_reveal_coretop_instance/up_down_counter_la0_inst_0/tm_u/pre_trig_cntr_cry_0_S0[0]</Navigation>
        </Message>
        <Message>
            <ID>1166052</ID>
            <Severity>Warning</Severity>
            <Dynamic>logical</Dynamic>
            <Dynamic>up_down_counter_reveal_coretop_instance/up_down_counter_la0_inst_0/tm_u/pre_trig_cntr_s_0_S1[7]</Dynamic>
            <Navigation>up_down_counter_reveal_coretop_instance/up_down_counter_la0_inst_0/tm_u/pre_trig_cntr_s_0_S1[7]</Navigation>
        </Message>
        <Message>
            <ID>1166052</ID>
            <Severity>Warning</Severity>
            <Dynamic>logical</Dynamic>
            <Dynamic>up_down_counter_reveal_coretop_instance/up_down_counter_la0_inst_0/tm_u/pre_trig_cntr_s_0_COUT[7]</Dynamic>
            <Navigation>up_down_counter_reveal_coretop_instance/up_down_counter_la0_inst_0/tm_u/pre_trig_cntr_s_0_COUT[7]</Navigation>
        </Message>
        <Message>
            <ID>1166052</ID>
            <Severity>Warning</Severity>
            <Dynamic>logical</Dynamic>
            <Dynamic>up_down_counter_reveal_coretop_instance/up_down_counter_la0_inst_0/tm_u/post_trig_cntr_cry_0_S0[0]</Dynamic>
            <Navigation>up_down_counter_reveal_coretop_instance/up_down_counter_la0_inst_0/tm_u/post_trig_cntr_cry_0_S0[0]</Navigation>
        </Message>
        <Message>
            <ID>1166052</ID>
            <Severity>Warning</Severity>
            <Dynamic>logical</Dynamic>
            <Dynamic>up_down_counter_reveal_coretop_instance/up_down_counter_la0_inst_0/tm_u/post_trig_cntr_s_0_S1[7]</Dynamic>
            <Navigation>up_down_counter_reveal_coretop_instance/up_down_counter_la0_inst_0/tm_u/post_trig_cntr_s_0_S1[7]</Navigation>
        </Message>
        <Message>
            <ID>1166052</ID>
            <Severity>Warning</Severity>
            <Dynamic>logical</Dynamic>
            <Dynamic>up_down_counter_reveal_coretop_instance/up_down_counter_la0_inst_0/tm_u/post_trig_cntr_s_0_COUT[7]</Dynamic>
            <Navigation>up_down_counter_reveal_coretop_instance/up_down_counter_la0_inst_0/tm_u/post_trig_cntr_s_0_COUT[7]</Navigation>
        </Message>
        <Message>
            <ID>1166052</ID>
            <Severity>Warning</Severity>
            <Dynamic>logical</Dynamic>
            <Dynamic>up_down_counter_reveal_coretop_instance/up_down_counter_la0_inst_0/tm_u/tm_rd_addr_cntr_cry_0_S0[0]</Dynamic>
            <Navigation>up_down_counter_reveal_coretop_instance/up_down_counter_la0_inst_0/tm_u/tm_rd_addr_cntr_cry_0_S0[0]</Navigation>
        </Message>
        <Message>
            <ID>1166052</ID>
            <Severity>Warning</Severity>
            <Dynamic>logical</Dynamic>
            <Dynamic>up_down_counter_reveal_coretop_instance/up_down_counter_la0_inst_0/tm_u/tm_rd_addr_cntr_s_0_S1[7]</Dynamic>
            <Navigation>up_down_counter_reveal_coretop_instance/up_down_counter_la0_inst_0/tm_u/tm_rd_addr_cntr_s_0_S1[7]</Navigation>
        </Message>
        <Message>
            <ID>1166052</ID>
            <Severity>Warning</Severity>
            <Dynamic>logical</Dynamic>
            <Dynamic>up_down_counter_reveal_coretop_instance/up_down_counter_la0_inst_0/tm_u/tm_rd_addr_cntr_s_0_COUT[7]</Dynamic>
            <Navigation>up_down_counter_reveal_coretop_instance/up_down_counter_la0_inst_0/tm_u/tm_rd_addr_cntr_s_0_COUT[7]</Navigation>
        </Message>
        <Message>
            <ID>1166052</ID>
            <Severity>Warning</Severity>
            <Dynamic>logical</Dynamic>
            <Dynamic>up_down_counter_reveal_coretop_instance/up_down_counter_la0_inst_0/GND</Dynamic>
            <Navigation>up_down_counter_reveal_coretop_instance/up_down_counter_la0_inst_0/GND</Navigation>
        </Message>
        <Message>
            <ID>1166052</ID>
            <Severity>Warning</Severity>
            <Dynamic>logical</Dynamic>
            <Dynamic>up_down_counter_reveal_coretop_instance/up_down_counter_la0_inst_0/VCC</Dynamic>
            <Navigation>up_down_counter_reveal_coretop_instance/up_down_counter_la0_inst_0/VCC</Navigation>
        </Message>
        <Message>
            <ID>1166052</ID>
            <Severity>Warning</Severity>
            <Dynamic>logical</Dynamic>
            <Dynamic>OSCH_inst_SEDSTDBY</Dynamic>
            <Navigation>OSCH_inst_SEDSTDBY</Navigation>
        </Message>
        <Message>
            <ID>1166052</ID>
            <Severity>Warning</Severity>
            <Dynamic>logical</Dynamic>
            <Dynamic>un2_out_cry_0_0_S0</Dynamic>
            <Navigation>un2_out_cry_0_0_S0</Navigation>
        </Message>
        <Message>
            <ID>1166052</ID>
            <Severity>Warning</Severity>
            <Dynamic>logical</Dynamic>
            <Dynamic>un2_out_cry_0_0_S1</Dynamic>
            <Navigation>un2_out_cry_0_0_S1</Navigation>
        </Message>
        <Message>
            <ID>1166052</ID>
            <Severity>Warning</Severity>
            <Dynamic>logical</Dynamic>
            <Dynamic>un2_out_s_7_0_S1</Dynamic>
            <Navigation>un2_out_s_7_0_S1</Navigation>
        </Message>
        <Message>
            <ID>1166052</ID>
            <Severity>Warning</Severity>
            <Dynamic>logical</Dynamic>
            <Dynamic>un2_out_s_7_0_COUT</Dynamic>
            <Navigation>un2_out_s_7_0_COUT</Navigation>
        </Message>
        <Message>
            <ID>1166052</ID>
            <Severity>Warning</Severity>
            <Dynamic>logical</Dynamic>
            <Dynamic>xo2chub/tdoa</Dynamic>
            <Navigation>xo2chub/tdoa</Navigation>
        </Message>
        <Message>
            <ID>1166052</ID>
            <Severity>Warning</Severity>
            <Dynamic>logical</Dynamic>
            <Dynamic>xo2chub/cdn</Dynamic>
            <Navigation>xo2chub/cdn</Navigation>
        </Message>
        <Message>
            <ID>1166052</ID>
            <Severity>Warning</Severity>
            <Dynamic>logical</Dynamic>
            <Dynamic>xo2chub/ip_enable[15]</Dynamic>
            <Navigation>xo2chub/ip_enable[15]</Navigation>
        </Message>
        <Message>
            <ID>1166052</ID>
            <Severity>Warning</Severity>
            <Dynamic>logical</Dynamic>
            <Dynamic>xo2chub/genblk7.un1_jtagf_u</Dynamic>
            <Navigation>xo2chub/genblk7.un1_jtagf_u</Navigation>
        </Message>
        <Message>
            <ID>1166052</ID>
            <Severity>Warning</Severity>
            <Dynamic>logical</Dynamic>
            <Dynamic>xo2chub/genblk7.un1_jtagf_u_1</Dynamic>
            <Navigation>xo2chub/genblk7.un1_jtagf_u_1</Navigation>
        </Message>
        <Message>
            <ID>1166052</ID>
            <Severity>Warning</Severity>
            <Dynamic>logical</Dynamic>
            <Dynamic>xo2chub/bit_count_cry_0_S0[0]</Dynamic>
            <Navigation>xo2chub/bit_count_cry_0_S0[0]</Navigation>
        </Message>
        <Message>
            <ID>1166052</ID>
            <Severity>Warning</Severity>
            <Dynamic>logical</Dynamic>
            <Dynamic>xo2chub/bit_count_cry_0_COUT[3]</Dynamic>
            <Navigation>xo2chub/bit_count_cry_0_COUT[3]</Navigation>
        </Message>
        <Message>
            <ID>1166052</ID>
            <Severity>Warning</Severity>
            <Dynamic>logical</Dynamic>
            <Dynamic>xo2chub/rom_rd_addr_cry_0_S0[0]</Dynamic>
            <Navigation>xo2chub/rom_rd_addr_cry_0_S0[0]</Navigation>
        </Message>
        <Message>
            <ID>1166052</ID>
            <Severity>Warning</Severity>
            <Dynamic>logical</Dynamic>
            <Dynamic>xo2chub/rom_rd_addr_s_0_S1[7]</Dynamic>
            <Navigation>xo2chub/rom_rd_addr_s_0_S1[7]</Navigation>
        </Message>
        <Message>
            <ID>1166052</ID>
            <Severity>Warning</Severity>
            <Dynamic>logical</Dynamic>
            <Dynamic>xo2chub/rom_rd_addr_s_0_COUT[7]</Dynamic>
            <Navigation>xo2chub/rom_rd_addr_s_0_COUT[7]</Navigation>
        </Message>
        <Message>
            <ID>1166052</ID>
            <Severity>Warning</Severity>
            <Dynamic>logical</Dynamic>
            <Dynamic>xo2chub/jtdo2_int_prm_16_0_0_S0</Dynamic>
            <Navigation>xo2chub/jtdo2_int_prm_16_0_0_S0</Navigation>
        </Message>
        <Message>
            <ID>1166052</ID>
            <Severity>Warning</Severity>
            <Dynamic>logical</Dynamic>
            <Dynamic>xo2chub/jtdo2_int_prm_16_0_0_S1</Dynamic>
            <Navigation>xo2chub/jtdo2_int_prm_16_0_0_S1</Navigation>
        </Message>
        <Message>
            <ID>1166052</ID>
            <Severity>Warning</Severity>
            <Dynamic>logical</Dynamic>
            <Dynamic>xo2chub/jtdo2_int_prm_15_0_0_S0</Dynamic>
            <Navigation>xo2chub/jtdo2_int_prm_15_0_0_S0</Navigation>
        </Message>
        <Message>
            <ID>1166052</ID>
            <Severity>Warning</Severity>
            <Dynamic>logical</Dynamic>
            <Dynamic>xo2chub/jtdo2_int_prm_15_0_0_S1</Dynamic>
            <Navigation>xo2chub/jtdo2_int_prm_15_0_0_S1</Navigation>
        </Message>
        <Message>
            <ID>1166052</ID>
            <Severity>Warning</Severity>
            <Dynamic>logical</Dynamic>
            <Dynamic>xo2chub/jtdo2_int_prm_13_0_0_S0</Dynamic>
            <Navigation>xo2chub/jtdo2_int_prm_13_0_0_S0</Navigation>
        </Message>
        <Message>
            <ID>1166052</ID>
            <Severity>Warning</Severity>
            <Dynamic>logical</Dynamic>
            <Dynamic>xo2chub/jtdo2_int_prm_13_0_0_S1</Dynamic>
            <Navigation>xo2chub/jtdo2_int_prm_13_0_0_S1</Navigation>
        </Message>
        <Message>
            <ID>1166052</ID>
            <Severity>Warning</Severity>
            <Dynamic>logical</Dynamic>
            <Dynamic>xo2chub/jtdo2_int_prm_11_0_0_S0</Dynamic>
            <Navigation>xo2chub/jtdo2_int_prm_11_0_0_S0</Navigation>
        </Message>
        <Message>
            <ID>1166052</ID>
            <Severity>Warning</Severity>
            <Dynamic>logical</Dynamic>
            <Dynamic>xo2chub/jtdo2_int_prm_11_0_0_S1</Dynamic>
            <Navigation>xo2chub/jtdo2_int_prm_11_0_0_S1</Navigation>
        </Message>
        <Message>
            <ID>1166052</ID>
            <Severity>Warning</Severity>
            <Dynamic>logical</Dynamic>
            <Dynamic>xo2chub/jtdo2_int_prm_9_0_0_S0</Dynamic>
            <Navigation>xo2chub/jtdo2_int_prm_9_0_0_S0</Navigation>
        </Message>
        <Message>
            <ID>1166052</ID>
            <Severity>Warning</Severity>
            <Dynamic>logical</Dynamic>
            <Dynamic>xo2chub/jtdo2_int_prm_9_0_0_S1</Dynamic>
            <Navigation>xo2chub/jtdo2_int_prm_9_0_0_S1</Navigation>
        </Message>
        <Message>
            <ID>1166052</ID>
            <Severity>Warning</Severity>
            <Dynamic>logical</Dynamic>
            <Dynamic>xo2chub/jtdo2_int_prm_7_0_0_S0</Dynamic>
            <Navigation>xo2chub/jtdo2_int_prm_7_0_0_S0</Navigation>
        </Message>
        <Message>
            <ID>1166052</ID>
            <Severity>Warning</Severity>
            <Dynamic>logical</Dynamic>
            <Dynamic>xo2chub/jtdo2_int_prm_7_0_0_S1</Dynamic>
            <Navigation>xo2chub/jtdo2_int_prm_7_0_0_S1</Navigation>
        </Message>
        <Message>
            <ID>1166052</ID>
            <Severity>Warning</Severity>
            <Dynamic>logical</Dynamic>
            <Dynamic>xo2chub/jtdo2_int_prm_5_0_0_S0</Dynamic>
            <Navigation>xo2chub/jtdo2_int_prm_5_0_0_S0</Navigation>
        </Message>
        <Message>
            <ID>1166052</ID>
            <Severity>Warning</Severity>
            <Dynamic>logical</Dynamic>
            <Dynamic>xo2chub/jtdo2_int_prm_5_0_0_S1</Dynamic>
            <Navigation>xo2chub/jtdo2_int_prm_5_0_0_S1</Navigation>
        </Message>
        <Message>
            <ID>1166052</ID>
            <Severity>Warning</Severity>
            <Dynamic>logical</Dynamic>
            <Dynamic>xo2chub/jtdo2_int_prm_3_0_0_S0</Dynamic>
            <Navigation>xo2chub/jtdo2_int_prm_3_0_0_S0</Navigation>
        </Message>
        <Message>
            <ID>1166052</ID>
            <Severity>Warning</Severity>
            <Dynamic>logical</Dynamic>
            <Dynamic>xo2chub/jtdo2_int_prm_3_0_0_S1</Dynamic>
            <Navigation>xo2chub/jtdo2_int_prm_3_0_0_S1</Navigation>
        </Message>
        <Message>
            <ID>1166052</ID>
            <Severity>Warning</Severity>
            <Dynamic>logical</Dynamic>
            <Dynamic>xo2chub/jtdo2_int_prm_1_0_0_S0</Dynamic>
            <Navigation>xo2chub/jtdo2_int_prm_1_0_0_S0</Navigation>
        </Message>
        <Message>
            <ID>1166052</ID>
            <Severity>Warning</Severity>
            <Dynamic>logical</Dynamic>
            <Dynamic>xo2chub/jtdo2_int_prm_1_0_0_COUT</Dynamic>
            <Navigation>xo2chub/jtdo2_int_prm_1_0_0_COUT</Navigation>
        </Message>
        <Message>
            <ID>1163101</ID>
            <Severity>Warning</Severity>
            <Dynamic>57</Dynamic>
        </Message>
    </Task>
    <Task name="Synplify_Synthesis">
        <Message>
            <ID>2120406</ID>
            <Severity>Error</Severity>
        </Message>
    </Task>
</BaliMessageLog>